Workbook

Sheet Cover Page
A1: Code | B1: SYB_23_1
A2: Version | B2: V1
A3: اسم القالب | B3: الناتج المحلي الإجمالي حسب طريقة الدخل والإنفاق بالأسعار الجارية
A4: Template Name | B4: Gross Domestic Product by Income and Expenditure Approach at Current Prices
A5: دورية البيانات | B5: سنوي
A6: Data Frequency | B6: Annual
A7: الجهة المصدرية | B7: دائرة الإحصاءات العامة / الحسابات القومية
A8: Data Source | B8: Department of Statistics/ National Account

Sheet Source Table
B2: ='Cover Page'!B4 -> Gross Domestic Product by Income and Expenditure Approach at Current Prices
B3: ='Cover Page'!B3 -> الناتج المحلي الإجمالي حسب طريقة الدخل والإنفاق بالأسعار الجارية
B4: Year | C4: 2023 | D4: السنة
B5: Items | D5: البند
B8: Compensation of Employees | D8: تعويضات العاملين
B9: Operating Surplus | D9: اجمالي فائض التشغيل والدخل المختلط
B10: Taxes on Production and Products | D10: الضرائب على الإنتاج والمنتجات
B11: Less: Subsidies | D11: ناقص : الإعانات
B12: Gross Domestic Product at Market prices Income Approach | D12: الناتج المحلي الإجمالي باسعار السوق طريقة الدخل
B13: Gov. Final Consumption Expenditures | D13: الإنفاق الاستهلاكي النهائي الحكومي
B14: Private Final Consumption Expenditures | D14: الإنفاق الاستهلاكي النهائي الخاص
B15: Fixed Capital Formation | D15: التكوين الرأسمالي الثابت
B16: Changes in Stocks | D16: التغير في المخزون
B17: Exports of Goods and Services | D17: صادرات السلع والخدمات
B18: Less: Imports of Goods and Services | D18: ناقص: واردات السلع والخدمات
B19: Gross Domestic Product at Market Prices Expenditure Approach | D19: الناتج المحلي الاجمالي بأسعار السوق طريقة الإنفاق

Sheet Relational DB
A1: Relational Sheet
A2: Measure_Name_Ar | B2: Measure_Name_En | C2: Measure_ID | D2: Unit_EN | E2: Unit_AR | F2: CL_INCOME_APPROACH_EN_V1 | G2: CL_INCOME_APPROACH_AR_V1 | H2: CL_EXPENDITURE_EN_V1 | I2: CL_EXPENDITURE_APPROACH_AR_V1 | J2: Obs_Value | K2: Time_Period_Y | L2: Time_Period_M
A3: اسم المؤشر | B3: Measure Name | C3: رمز المؤشر | D3: Unit | E3: الوحدة | F3: INCOME APPROACH | G3: طريقة الدخل | H3: EXPENDITURE APPROACH | I3: طريقة الانفاق | J3: قيمة المؤشر | K3: سنة فترة القياس | L3: شهر فترة القياس
A4: الناتج المحلي الإجمالي بالأسعار الجارية | B4: Gross Domestic Product at Current Prices | C4: M1 | D4: Million JD | E4: مليون دينار | F4: =+'Source Table'!$B$8 -> Compensation of Employees | G4: =+'Source Table'!$D$8 -> تعويضات العاملين | H4: Not Applicable | I4: لا ينطبق | J4: 5932.657 | K4: 2008
A5: الناتج المحلي الإجمالي بالأسعار الجارية | B5: Gross Domestic Product at Current Prices | C5: M1 | D5: Million JD | E5: مليون دينار | F5: =+'Source Table'!$B$9 -> Operating Surplus | G5: =+'Source Table'!$D$9 -> اجمالي فائض التشغيل والدخل المختلط | H5: Not Applicable | I5: لا ينطبق | J5: 8055.2966 | K5: 2008
A6: الناتج المحلي الإجمالي بالأسعار الجارية | B6: Gross Domestic Product at Current Prices | C6: M1 | D6: Million JD | E6: مليون دينار | F6: =+'Source Table'!$B$10 -> Taxes on Production and Products | G6: =+'Source Table'!$D$10 -> الضرائب على الإنتاج والمنتجات | H6: Not Applicable | I6: لا ينطبق | J6: 2511.1894 | K6: 2008
A7: الناتج المحلي الإجمالي بالأسعار الجارية | B7: Gross Domestic Product at Current Prices | C7: M1 | D7: Million JD | E7: مليون دينار | F7: =+'Source Table'!$B$11 -> Less: Subsidies | G7: =+'Source Table'!$D$11 -> ناقص : الإعانات | H7: Not Applicable | I7: لا ينطبق | J7: 419 | K7: 2008
A8: الناتج المحلي الإجمالي بالأسعار الجارية | B8: Gross Domestic Product at Current Prices | C8: M1 | D8: Million JD | E8: مليون دينار | F8: =+'Source Table'!$B$12 -> Gross Domestic Product at Market prices Income Approach | G8: =+'Source Table'!$D$12 -> الناتج المحلي الإجمالي باسعار السوق طريقة الدخل | H8: Not Applicable | I8: لا ينطبق | J8: 16080.143 | K8: 2008
A9: الناتج المحلي الإجمالي بالأسعار الجارية | B9: Gross Domestic Product at Current Prices | C9: M1 | D9: Million JD | E9: مليون دينار | F9: Not Applicable | G9: لا ينطبق | H9: =+'Source Table'!$B$13 -> Gov. Final Consumption Expenditures | I9: =+'Source Table'!$D$13 -> الإنفاق الاستهلاكي النهائي الحكومي | J9: 2954.5673 | K9: 2008
A10: الناتج المحلي الإجمالي بالأسعار الجارية | B10: Gross Domestic Product at Current Prices | C10: M1 | D10: Million JD | E10: مليون دينار | F10: Not Applicable | G10: لا ينطبق | H10: =+'Source Table'!$B$14 -> Private Final Consumption Expenditures | I10: =+'Source Table'!$D$14 -> الإنفاق الاستهلاكي النهائي الخاص | J10: 11961.861 | K10: 2008
A11: الناتج المحلي الإجمالي بالأسعار الجارية | B11: Gross Domestic Product at Current Prices | C11: M1 | D11: Million JD | E11: مليون دينار | F11: Not Applicable | G11: لا ينطبق | H11: =+'Source Table'!$B$15 -> Fixed Capital Formation | I11: =+'Source Table'!$D$15 -> التكوين الرأسمالي الثابت | J11: 728.83321 | K11: 2008
A12: الناتج المحلي الإجمالي بالأسعار الجارية | B12: Gross Domestic Product at Current Prices | C12: M1 | D12: Million JD | E12: مليون دينار | F12: Not Applicable | G12: لا ينطبق | H12: =+'Source Table'!$B$16 -> Changes in Stocks | I12: =+'Source Table'!$D$16 -> التغير في المخزون | J12: 5067.8812 | K12: 2008
A13: الناتج المحلي الإجمالي بالأسعار الجارية | B13: Gross Domestic Product at Current Prices | C13: M1 | D13: Million JD | E13: مليون دينار | F13: Not Applicable | G13: لا ينطبق | H13: =+'Source Table'!$B$17 -> Exports of Goods and Services | I13: =+'Source Table'!$D$17 -> صادرات السلع والخدمات | J13: 9013 | K13: 2008
A14: الناتج المحلي الإجمالي بالأسعار الجارية | B14: Gross Domestic Product at Current Prices | C14: M1 | D14: Million JD | E14: مليون دينار | F14: Not Applicable | G14: لا ينطبق | H14: =+'Source Table'!$B$18 -> Less: Imports of Goods and Services | I14: =+'Source Table'!$D$18 -> ناقص: واردات السلع والخدمات | J14: 13646 | K14: 2008
A15: الناتج المحلي الإجمالي بالأسعار الجارية | B15: Gross Domestic Product at Current Prices | C15: M1 | D15: Million JD | E15: مليون دينار | F15: Not Applicable | G15: لا ينطبق | H15: =+'Source Table'!$B$19 -> Gross Domestic Product at Market Prices Expenditure Approach | I15: =+'Source Table'!$D$19 -> الناتج المحلي الاجمالي بأسعار السوق طريقة الإنفاق | J15: 16080.143 | K15: 2008
A16: الناتج المحلي الإجمالي بالأسعار الجارية | B16: Gross Domestic Product at Current Prices | C16: M1 | D16: Million JD | E16: مليون دينار | F16: =+'Source Table'!$B$8 -> Compensation of Employees | G16: =+'Source Table'!$D$8 -> تعويضات العاملين | H16: Not Applicable | I16: لا ينطبق | J16: 6784.1082 | K16: =+K4+1 -> 2009
A17: الناتج المحلي الإجمالي بالأسعار الجارية | B17: Gross Domestic Product at Current Prices | C17: M1 | D17: Million JD | E17: مليون دينار | F17: =+'Source Table'!$B$9 -> Operating Surplus | G17: =+'Source Table'!$D$9 -> اجمالي فائض التشغيل والدخل المختلط | H17: Not Applicable | I17: لا ينطبق | J17: 8309.1607 | K17: =+K5+1 -> 2009
A18: الناتج المحلي الإجمالي بالأسعار الجارية | B18: Gross Domestic Product at Current Prices | C18: M1 | D18: Million JD | E18: مليون دينار | F18: =+'Source Table'!$B$10 -> Taxes on Production and Products | G18: =+'Source Table'!$D$10 -> الضرائب على الإنتاج والمنتجات | H18: Not Applicable | I18: لا ينطبق | J18: 2514.6231 | K18: =+K6+1 -> 2009
A19: الناتج المحلي الإجمالي بالأسعار الجارية | B19: Gross Domestic Product at Current Prices | C19: M1 | D19: Million JD | E19: مليون دينار | F19: =+'Source Table'!$B$11 -> Less: Subsidies | G19: =+'Source Table'!$D$11 -> ناقص : الإعانات | H19: Not Applicable | I19: لا ينطبق | J19: 186 | K19: =+K7+1 -> 2009
A20: الناتج المحلي الإجمالي بالأسعار الجارية | B20: Gross Domestic Product at Current Prices | C20: M1 | D20: Million JD | E20: مليون دينار | F20: =+'Source Table'!$B$12 -> Gross Domestic Product at Market prices Income Approach | G20: =+'Source Table'!$D$12 -> الناتج المحلي الإجمالي باسعار السوق طريقة الدخل | H20: Not Applicable | I20: لا ينطبق | J20: 17421.892 | K20: =+K8+1 -> 2009
A21: الناتج المحلي الإجمالي بالأسعار الجارية | B21: Gross Domestic Product at Current Prices | C21: M1 | D21: Million JD | E21: مليون دينار | F21: Not Applicable | G21: لا ينطبق | H21: =+'Source Table'!$B$13 -> Gov. Final Consumption Expenditures | I21: =+'Source Table'!$D$13 -> الإنفاق الاستهلاكي النهائي الحكومي | J21: 3645.0552 | K21: =+K9+1 -> 2009
A22: الناتج المحلي الإجمالي بالأسعار الجارية | B22: Gross Domestic Product at Current Prices | C22: M1 | D22: Million JD | E22: مليون دينار | F22: Not Applicable | G22: لا ينطبق | H22: =+'Source Table'!$B$14 -> Private Final Consumption Expenditures | I22: =+'Source Table'!$D$14 -> الإنفاق الاستهلاكي النهائي الخاص | J22: 11940.927 | K22: =+K10+1 -> 2009
A23: الناتج المحلي الإجمالي بالأسعار الجارية | B23: Gross Domestic Product at Current Prices | C23: M1 | D23: Million JD | E23: مليون دينار | F23: Not Applicable | G23: لا ينطبق | H23: =+'Source Table'!$B$15 -> Fixed Capital Formation | I23: =+'Source Table'!$D$15 -> التكوين الرأسمالي الثابت | J23: 314.1891 | K23: =+K11+1 -> 2009
A24: الناتج المحلي الإجمالي بالأسعار الجارية | B24: Gross Domestic Product at Current Prices | C24: M1 | D24: Million JD | E24: مليون دينار | F24: Not Applicable | G24: لا ينطبق | H24: =+'Source Table'!$B$16 -> Changes in Stocks | I24: =+'Source Table'!$D$16 -> التغير في المخزون | J24: 5354.7207 | K24: =+K12+1 -> 2009
A25: الناتج المحلي الإجمالي بالأسعار الجارية | B25: Gross Domestic Product at Current Prices | C25: M1 | D25: Million JD | E25: مليون دينار | F25: Not Applicable | G25: لا ينطبق | H25: =+'Source Table'!$B$17 -> Exports of Goods and Services | I25: =+'Source Table'!$D$17 -> صادرات السلع والخدمات | J25: 7853 | K25: =+K13+1 -> 2009
A26: الناتج المحلي الإجمالي بالأسعار الجارية | B26: Gross Domestic Product at Current Prices | C26: M1 | D26: Million JD | E26: مليون دينار | F26: Not Applicable | G26: لا ينطبق | H26: =+'Source Table'!$B$18 -> Less: Imports of Goods and Services | I26: =+'Source Table'!$D$18 -> ناقص: واردات السلع والخدمات | J26: 11686 | K26: =+K14+1 -> 2009
A27: الناتج المحلي الإجمالي بالأسعار الجارية | B27: Gross Domestic Product at Current Prices | C27: M1 | D27: Million JD | E27: مليون دينار | F27: Not Applicable | G27: لا ينطبق | H27: =+'Source Table'!$B$19 -> Gross Domestic Product at Market Prices Expenditure Approach | I27: =+'Source Table'!$D$19 -> الناتج المحلي الاجمالي بأسعار السوق طريقة الإنفاق | J27: 17421.892 | K27: =+K15+1 -> 2009
A28: الناتج المحلي الإجمالي بالأسعار الجارية | B28: Gross Domestic Product at Current Prices | C28: M1 | D28: Million JD | E28: مليون دينار | F28: =+'Source Table'!$B$8 -> Compensation of Employees | G28: =+'Source Table'!$D$8 -> تعويضات العاملين | H28: Not Applicable | I28: لا ينطبق | J28: 7108.6278 | K28: =+K16+1 -> 2010
A29: الناتج المحلي الإجمالي بالأسعار الجارية | B29: Gross Domestic Product at Current Prices | C29: M1 | D29: Million JD | E29: مليون دينار | F29: =+'Source Table'!$B$9 -> Operating Surplus | G29: =+'Source Table'!$D$9 -> اجمالي فائض التشغيل والدخل المختلط | H29: Not Applicable | I29: لا ينطبق | J29: 9300.2354 | K29: =+K17+1 -> 2010
A30: الناتج المحلي الإجمالي بالأسعار الجارية | B30: Gross Domestic Product at Current Prices | C30: M1 | D30: Million JD | E30: مليون دينار | F30: =+'Source Table'!$B$10 -> Taxes on Production and Products | G30: =+'Source Table'!$D$10 -> الضرائب على الإنتاج والمنتجات | H30: Not Applicable | I30: لا ينطبق | J30: 3049.1379 | K30: =+K18+1 -> 2010
A31: الناتج المحلي الإجمالي بالأسعار الجارية | B31: Gross Domestic Product at Current Prices | C31: M1 | D31: Million JD | E31: مليون دينار | F31: =+'Source Table'!$B$11 -> Less: Subsidies | G31: =+'Source Table'!$D$11 -> ناقص : الإعانات | H31: Not Applicable | I31: لا ينطبق | J31: 193 | K31: =+K19+1 -> 2010
A32: الناتج المحلي الإجمالي بالأسعار الجارية | B32: Gross Domestic Product at Current Prices | C32: M1 | D32: Million JD | E32: مليون دينار | F32: =+'Source Table'!$B$12 -> Gross Domestic Product at Market prices Income Approach | G32: =+'Source Table'!$D$12 -> الناتج المحلي الإجمالي باسعار السوق طريقة الدخل | H32: Not Applicable | I32: لا ينطبق | J32: 19265.001 | K32: =+K20+1 -> 2010
A33: الناتج المحلي الإجمالي بالأسعار الجارية | B33: Gross Domestic Product at Current Prices | C33: M1 | D33: Million JD | E33: مليون دينار | F33: Not Applicable | G33: لا ينطبق | H33: =+'Source Table'!$B$13 -> Gov. Final Consumption Expenditures | I33: =+'Source Table'!$D$13 -> الإنفاق الاستهلاكي النهائي الحكومي | J33: 3708.134 | K33: =+K21+1 -> 2010
A34: الناتج المحلي الإجمالي بالأسعار الجارية | B34: Gross Domestic Product at Current Prices | C34: M1 | D34: Million JD | E34: مليون دينار | F34: Not Applicable | G34: لا ينطبق | H34: =+'Source Table'!$B$14 -> Private Final Consumption Expenditures | I34: =+'Source Table'!$D$14 -> الإنفاق الاستهلاكي النهائي الخاص | J34: 12703.627 | K34: =+K22+1 -> 2010
A35: الناتج المحلي الإجمالي بالأسعار الجارية | B35: Gross Domestic Product at Current Prices | C35: M1 | D35: Million JD | E35: مليون دينار | F35: Not Applicable | G35: لا ينطبق | H35: =+'Source Table'!$B$15 -> Fixed Capital Formation | I35: =+'Source Table'!$D$15 -> التكوين الرأسمالي الثابت | J35: 805.77748 | K35: =+K23+1 -> 2010
A36: الناتج المحلي الإجمالي بالأسعار الجارية | B36: Gross Domestic Product at Current Prices | C36: M1 | D36: Million JD | E36: مليون دينار | F36: Not Applicable | G36: لا ينطبق | H36: =+'Source Table'!$B$16 -> Changes in Stocks | I36: =+'Source Table'!$D$16 -> التغير في المخزون | J36: 5944.4628 | K36: =+K24+1 -> 2010
A37: الناتج المحلي الإجمالي بالأسعار الجارية | B37: Gross Domestic Product at Current Prices | C37: M1 | D37: Million JD | E37: مليون دينار | F37: Not Applicable | G37: لا ينطبق | H37: =+'Source Table'!$B$17 -> Exports of Goods and Services | I37: =+'Source Table'!$D$17 -> صادرات السلع والخدمات | J37: 9054 | K37: =+K25+1 -> 2010
A38: الناتج المحلي الإجمالي بالأسعار الجارية | B38: Gross Domestic Product at Current Prices | C38: M1 | D38: Million JD | E38: مليون دينار | F38: Not Applicable | G38: لا ينطبق | H38: =+'Source Table'!$B$18 -> Less: Imports of Goods and Services | I38: =+'Source Table'!$D$18 -> ناقص: واردات السلع والخدمات | J38: 12951 | K38: =+K26+1 -> 2010
A39: الناتج المحلي الإجمالي بالأسعار الجارية | B39: Gross Domestic Product at Current Prices | C39: M1 | D39: Million JD | E39: مليون دينار | F39: Not Applicable | G39: لا ينطبق | H39: =+'Source Table'!$B$19 -> Gross Domestic Product at Market Prices Expenditure Approach | I39: =+'Source Table'!$D$19 -> الناتج المحلي الاجمالي بأسعار السوق طريقة الإنفاق | J39: 19265.001 | K39: =+K27+1 -> 2010
A40: الناتج المحلي الإجمالي بالأسعار الجارية | B40: Gross Domestic Product at Current Prices | C40: M1 | D40: Million JD | E40: مليون دينار | F40: =+'Source Table'!$B$8 -> Compensation of Employees | G40: =+'Source Table'!$D$8 -> تعويضات العاملين | H40: Not Applicable | I40: لا ينطبق | J40: 7866.5734 | K40: =+K28+1 -> 2011
A41: الناتج المحلي الإجمالي بالأسعار الجارية | B41: Gross Domestic Product at Current Prices | C41: M1 | D41: Million JD | E41: مليون دينار | F41: =+'Source Table'!$B$9 -> Operating Surplus | G41: =+'Source Table'!$D$9 -> اجمالي فائض التشغيل والدخل المختلط | H41: Not Applicable | I41: لا ينطبق | J41: 9947.2353 | K41: =+K29+1 -> 2011
A42: الناتج المحلي الإجمالي بالأسعار الجارية | B42: Gross Domestic Product at Current Prices | C42: M1 | D42: Million JD | E42: مليون دينار | F42: =+'Source Table'!$B$10 -> Taxes on Production and Products | G42: =+'Source Table'!$D$10 -> الضرائب على الإنتاج والمنتجات | H42: Not Applicable | I42: لا ينطبق | J42: 3945.3372 | K42: =+K30+1 -> 2011
A43: الناتج المحلي الإجمالي بالأسعار الجارية | B43: Gross Domestic Product at Current Prices | C43: M1 | D43: Million JD | E43: مليون دينار | F43: =+'Source Table'!$B$11 -> Less: Subsidies | G43: =+'Source Table'!$D$11 -> ناقص : الإعانات | H43: Not Applicable | I43: لا ينطبق | J43: 797 | K43: =+K31+1 -> 2011
A44: الناتج المحلي الإجمالي بالأسعار الجارية | B44: Gross Domestic Product at Current Prices | C44: M1 | D44: Million JD | E44: مليون دينار | F44: =+'Source Table'!$B$12 -> Gross Domestic Product at Market prices Income Approach | G44: =+'Source Table'!$D$12 -> الناتج المحلي الإجمالي باسعار السوق طريقة الدخل | H44: Not Applicable | I44: لا ينطبق | J44: 20962.146 | K44: =+K32+1 -> 2011
A45: الناتج المحلي الإجمالي بالأسعار الجارية | B45: Gross Domestic Product at Current Prices | C45: M1 | D45: Million JD | E45: مليون دينار | F45: Not Applicable | G45: لا ينطبق | H45: =+'Source Table'!$B$13 -> Gov. Final Consumption Expenditures | I45: =+'Source Table'!$D$13 -> الإنفاق الاستهلاكي النهائي الحكومي | J45: 4206.0062 | K45: =+K33+1 -> 2011
A46: الناتج المحلي الإجمالي بالأسعار الجارية | B46: Gross Domestic Product at Current Prices | C46: M1 | D46: Million JD | E46: مليون دينار | F46: Not Applicable | G46: لا ينطبق | H46: =+'Source Table'!$B$14 -> Private Final Consumption Expenditures | I46: =+'Source Table'!$D$14 -> الإنفاق الاستهلاكي النهائي الخاص | J46: 15466.821 | K46: =+K34+1 -> 2011
A47: الناتج المحلي الإجمالي بالأسعار الجارية | B47: Gross Domestic Product at Current Prices | C47: M1 | D47: Million JD | E47: مليون دينار | F47: Not Applicable | G47: لا ينطبق | H47: =+'Source Table'!$B$15 -> Fixed Capital Formation | I47: =+'Source Table'!$D$15 -> التكوين الرأسمالي الثابت | J47: 692.49842 | K47: =+K35+1 -> 2011
A48: الناتج المحلي الإجمالي بالأسعار الجارية | B48: Gross Domestic Product at Current Prices | C48: M1 | D48: Million JD | E48: مليون دينار | F48: Not Applicable | G48: لا ينطبق | H48: =+'Source Table'!$B$16 -> Changes in Stocks | I48: =+'Source Table'!$D$16 -> التغير في المخزون | J48: 5962.8205 | K48: =+K36+1 -> 2011
A49: الناتج المحلي الإجمالي بالأسعار الجارية | B49: Gross Domestic Product at Current Prices | C49: M1 | D49: Million JD | E49: مليون دينار | F49: Not Applicable | G49: لا ينطبق | H49: =+'Source Table'!$B$17 -> Exports of Goods and Services | I49: =+'Source Table'!$D$17 -> صادرات السلع والخدمات | J49: 9758 | K49: =+K37+1 -> 2011
A50: الناتج المحلي الإجمالي بالأسعار الجارية | B50: Gross Domestic Product at Current Prices | C50: M1 | D50: Million JD | E50: مليون دينار | F50: Not Applicable | G50: لا ينطبق | H50: =+'Source Table'!$B$18 -> Less: Imports of Goods and Services | I50: =+'Source Table'!$D$18 -> ناقص: واردات السلع والخدمات | J50: 15124 | K50: =+K38+1 -> 2011
A51: الناتج المحلي الإجمالي بالأسعار الجارية | B51: Gross Domestic Product at Current Prices | C51: M1 | D51: Million JD | E51: مليون دينار | F51: Not Applicable | G51: لا ينطبق | H51: =+'Source Table'!$B$19 -> Gross Domestic Product at Market Prices Expenditure Approach | I51: =+'Source Table'!$D$19 -> الناتج المحلي الاجمالي بأسعار السوق طريقة الإنفاق | J51: 20962.146 | K51: =+K39+1 -> 2011
A52: الناتج المحلي الإجمالي بالأسعار الجارية | B52: Gross Domestic Product at Current Prices | C52: M1 | D52: Million JD | E52: مليون دينار | F52: =+'Source Table'!$B$8 -> Compensation of Employees | G52: =+'Source Table'!$D$8 -> تعويضات العاملين | H52: Not Applicable | I52: لا ينطبق | J52: 8514.5124 | K52: =+K40+1 -> 2012
A53: الناتج المحلي الإجمالي بالأسعار الجارية | B53: Gross Domestic Product at Current Prices | C53: M1 | D53: Million JD | E53: مليون دينار | F53: =+'Source Table'!$B$9 -> Operating Surplus | G53: =+'Source Table'!$D$9 -> اجمالي فائض التشغيل والدخل المختلط | H53: Not Applicable | I53: لا ينطبق | J53: 10598.968 | K53: =+K41+1 -> 2012
A54: الناتج المحلي الإجمالي بالأسعار الجارية | B54: Gross Domestic Product at Current Prices | C54: M1 | D54: Million JD | E54: مليون دينار | F54: =+'Source Table'!$B$10 -> Taxes on Production and Products | G54: =+'Source Table'!$D$10 -> الضرائب على الإنتاج والمنتجات | H54: Not Applicable | I54: لا ينطبق | J54: 4236.0583 | K54: =+K42+1 -> 2012
A55: الناتج المحلي الإجمالي بالأسعار الجارية | B55: Gross Domestic Product at Current Prices | C55: M1 | D55: Million JD | E55: مليون دينار | F55: =+'Source Table'!$B$11 -> Less: Subsidies | G55: =+'Source Table'!$D$11 -> ناقص : الإعانات | H55: Not Applicable | I55: لا ينطبق | J55: 889 | K55: =+K43+1 -> 2012
A56: الناتج المحلي الإجمالي بالأسعار الجارية | B56: Gross Domestic Product at Current Prices | C56: M1 | D56: Million JD | E56: مليون دينار | F56: =+'Source Table'!$B$12 -> Gross Domestic Product at Market prices Income Approach | G56: =+'Source Table'!$D$12 -> الناتج المحلي الإجمالي باسعار السوق طريقة الدخل | H56: Not Applicable | I56: لا ينطبق | J56: 22460.539 | K56: =+K44+1 -> 2012
A57: الناتج المحلي الإجمالي بالأسعار الجارية | B57: Gross Domestic Product at Current Prices | C57: M1 | D57: Million JD | E57: مليون دينار | F57: Not Applicable | G57: لا ينطبق | H57: =+'Source Table'!$B$13 -> Gov. Final Consumption Expenditures | I57: =+'Source Table'!$D$13 -> الإنفاق الاستهلاكي النهائي الحكومي | J57: 4292.7396 | K57: =+K45+1 -> 2012
A58: الناتج المحلي الإجمالي بالأسعار الجارية | B58: Gross Domestic Product at Current Prices | C58: M1 | D58: Million JD | E58: مليون دينار | F58: Not Applicable | G58: لا ينطبق | H58: =+'Source Table'!$B$14 -> Private Final Consumption Expenditures | I58: =+'Source Table'!$D$14 -> الإنفاق الاستهلاكي النهائي الخاص | J58: 17353.402 | K58: =+K46+1 -> 2012
A59: الناتج المحلي الإجمالي بالأسعار الجارية | B59: Gross Domestic Product at Current Prices | C59: M1 | D59: Million JD | E59: مليون دينار | F59: Not Applicable | G59: لا ينطبق | H59: =+'Source Table'!$B$15 -> Fixed Capital Formation | I59: =+'Source Table'!$D$15 -> التكوين الرأسمالي الثابت | J59: 1506.8253 | K59: =+K47+1 -> 2012
A60: الناتج المحلي الإجمالي بالأسعار الجارية | B60: Gross Domestic Product at Current Prices | C60: M1 | D60: Million JD | E60: مليون دينار | F60: Not Applicable | G60: لا ينطبق | H60: =+'Source Table'!$B$16 -> Changes in Stocks | I60: =+'Source Table'!$D$16 -> التغير في المخزون | J60: 5462.5724 | K60: =+K48+1 -> 2012
A61: الناتج المحلي الإجمالي بالأسعار الجارية | B61: Gross Domestic Product at Current Prices | C61: M1 | D61: Million JD | E61: مليون دينار | F61: Not Applicable | G61: لا ينطبق | H61: =+'Source Table'!$B$17 -> Exports of Goods and Services | I61: =+'Source Table'!$D$17 -> صادرات السلع والخدمات | J61: 10158 | K61: =+K49+1 -> 2012
A62: الناتج المحلي الإجمالي بالأسعار الجارية | B62: Gross Domestic Product at Current Prices | C62: M1 | D62: Million JD | E62: مليون دينار | F62: Not Applicable | G62: لا ينطبق | H62: =+'Source Table'!$B$18 -> Less: Imports of Goods and Services | I62: =+'Source Table'!$D$18 -> ناقص: واردات السلع والخدمات | J62: 16313 | K62: =+K50+1 -> 2012
A63: الناتج المحلي الإجمالي بالأسعار الجارية | B63: Gross Domestic Product at Current Prices | C63: M1 | D63: Million JD | E63: مليون دينار | F63: Not Applicable | G63: لا ينطبق | H63: =+'Source Table'!$B$19 -> Gross Domestic Product at Market Prices Expenditure Approach | I63: =+'Source Table'!$D$19 -> الناتج المحلي الاجمالي بأسعار السوق طريقة الإنفاق | J63: 22460.539 | K63: =+K51+1 -> 2012
A64: الناتج المحلي الإجمالي بالأسعار الجارية | B64: Gross Domestic Product at Current Prices | C64: M1 | D64: Million JD | E64: مليون دينار | F64: =+'Source Table'!$B$8 -> Compensation of Employees | G64: =+'Source Table'!$D$8 -> تعويضات العاملين | H64: Not Applicable | I64: لا ينطبق | J64: 9181.1525 | K64: =+K52+1 -> 2013
A65: الناتج المحلي الإجمالي بالأسعار الجارية | B65: Gross Domestic Product at Current Prices | C65: M1 | D65: Million JD | E65: مليون دينار | F65: =+'Source Table'!$B$9 -> Operating Surplus | G65: =+'Source Table'!$D$9 -> اجمالي فائض التشغيل والدخل المختلط | H65: Not Applicable | I65: لا ينطبق | J65: 11755.258 | K65: =+K53+1 -> 2013
A66: الناتج المحلي الإجمالي بالأسعار الجارية | B66: Gross Domestic Product at Current Prices | C66: M1 | D66: Million JD | E66: مليون دينار | F66: =+'Source Table'!$B$10 -> Taxes on Production and Products | G66: =+'Source Table'!$D$10 -> الضرائب على الإنتاج والمنتجات | H66: Not Applicable | I66: لا ينطبق | J66: 3786.2418 | K66: =+K54+1 -> 2013
A67: الناتج المحلي الإجمالي بالأسعار الجارية | B67: Gross Domestic Product at Current Prices | C67: M1 | D67: Million JD | E67: مليون دينار | F67: =+'Source Table'!$B$11 -> Less: Subsidies | G67: =+'Source Table'!$D$11 -> ناقص : الإعانات | H67: Not Applicable | I67: لا ينطبق | J67: 260 | K67: =+K55+1 -> 2013
A68: الناتج المحلي الإجمالي بالأسعار الجارية | B68: Gross Domestic Product at Current Prices | C68: M1 | D68: Million JD | E68: مليون دينار | F68: =+'Source Table'!$B$12 -> Gross Domestic Product at Market prices Income Approach | G68: =+'Source Table'!$D$12 -> الناتج المحلي الإجمالي باسعار السوق طريقة الدخل | H68: Not Applicable | I68: لا ينطبق | J68: 24462.653 | K68: =+K56+1 -> 2013
A69: الناتج المحلي الإجمالي بالأسعار الجارية | B69: Gross Domestic Product at Current Prices | C69: M1 | D69: Million JD | E69: مليون دينار | F69: Not Applicable | G69: لا ينطبق | H69: =+'Source Table'!$B$13 -> Gov. Final Consumption Expenditures | I69: =+'Source Table'!$D$13 -> الإنفاق الاستهلاكي النهائي الحكومي | J69: 4468.4591 | K69: =+K57+1 -> 2013
A70: الناتج المحلي الإجمالي بالأسعار الجارية | B70: Gross Domestic Product at Current Prices | C70: M1 | D70: Million JD | E70: مليون دينار | F70: Not Applicable | G70: لا ينطبق | H70: =+'Source Table'!$B$14 -> Private Final Consumption Expenditures | I70: =+'Source Table'!$D$14 -> الإنفاق الاستهلاكي النهائي الخاص | J70: 20547.056 | K70: =+K58+1 -> 2013
A71: الناتج المحلي الإجمالي بالأسعار الجارية | B71: Gross Domestic Product at Current Prices | C71: M1 | D71: Million JD | E71: مليون دينار | F71: Not Applicable | G71: لا ينطبق | H71: =+'Source Table'!$B$15 -> Fixed Capital Formation | I71: =+'Source Table'!$D$15 -> التكوين الرأسمالي الثابت | J71: 1038.7476 | K71: =+K59+1 -> 2013
A72: الناتج المحلي الإجمالي بالأسعار الجارية | B72: Gross Domestic Product at Current Prices | C72: M1 | D72: Million JD | E72: مليون دينار | F72: Not Applicable | G72: لا ينطبق | H72: =+'Source Table'!$B$16 -> Changes in Stocks | I72: =+'Source Table'!$D$16 -> التغير في المخزون | J72: 5468.3901 | K72: =+K60+1 -> 2013
A73: الناتج المحلي الإجمالي بالأسعار الجارية | B73: Gross Domestic Product at Current Prices | C73: M1 | D73: Million JD | E73: مليون دينار | F73: Not Applicable | G73: لا ينطبق | H73: =+'Source Table'!$B$17 -> Exports of Goods and Services | I73: =+'Source Table'!$D$17 -> صادرات السلع والخدمات | J73: 10102 | K73: =+K61+1 -> 2013
A74: الناتج المحلي الإجمالي بالأسعار الجارية | B74: Gross Domestic Product at Current Prices | C74: M1 | D74: Million JD | E74: مليون دينار | F74: Not Applicable | G74: لا ينطبق | H74: =+'Source Table'!$B$18 -> Less: Imports of Goods and Services | I74: =+'Source Table'!$D$18 -> ناقص: واردات السلع والخدمات | J74: 17162 | K74: =+K62+1 -> 2013
A75: الناتج المحلي الإجمالي بالأسعار الجارية | B75: Gross Domestic Product at Current Prices | C75: M1 | D75: Million JD | E75: مليون دينار | F75: Not Applicable | G75: لا ينطبق | H75: =+'Source Table'!$B$19 -> Gross Domestic Product at Market Prices Expenditure Approach | I75: =+'Source Table'!$D$19 -> الناتج المحلي الاجمالي بأسعار السوق طريقة الإنفاق | J75: 24462.653 | K75: =+K63+1 -> 2013
A76: الناتج المحلي الإجمالي بالأسعار الجارية | B76: Gross Domestic Product at Current Prices | C76: M1 | D76: Million JD | E76: مليون دينار | F76: =+'Source Table'!$B$8 -> Compensation of Employees | G76: =+'Source Table'!$D$8 -> تعويضات العاملين | H76: Not Applicable | I76: لا ينطبق | J76: 9716.8847 | K76: =+K64+1 -> 2014
A77: الناتج المحلي الإجمالي بالأسعار الجارية | B77: Gross Domestic Product at Current Prices | C77: M1 | D77: Million JD | E77: مليون دينار | F77: =+'Source Table'!$B$9 -> Operating Surplus | G77: =+'Source Table'!$D$9 -> اجمالي فائض التشغيل والدخل المختلط | H77: Not Applicable | I77: لا ينطبق | J77: 12666.099 | K77: =+K65+1 -> 2014
A78: الناتج المحلي الإجمالي بالأسعار الجارية | B78: Gross Domestic Product at Current Prices | C78: M1 | D78: Million JD | E78: مليون دينار | F78: =+'Source Table'!$B$10 -> Taxes on Production and Products | G78: =+'Source Table'!$D$10 -> الضرائب على الإنتاج والمنتجات | H78: Not Applicable | I78: لا ينطبق | J78: 3996.8429 | K78: =+K66+1 -> 2014
A79: الناتج المحلي الإجمالي بالأسعار الجارية | B79: Gross Domestic Product at Current Prices | C79: M1 | D79: Million JD | E79: مليون دينار | F79: =+'Source Table'!$B$11 -> Less: Subsidies | G79: =+'Source Table'!$D$11 -> ناقص : الإعانات | H79: Not Applicable | I79: لا ينطبق | J79: 218 | K79: =+K67+1 -> 2014
A80: الناتج المحلي الإجمالي بالأسعار الجارية | B80: Gross Domestic Product at Current Prices | C80: M1 | D80: Million JD | E80: مليون دينار | F80: =+'Source Table'!$B$12 -> Gross Domestic Product at Market prices Income Approach | G80: =+'Source Table'!$D$12 -> الناتج المحلي الإجمالي باسعار السوق طريقة الدخل | H80: Not Applicable | I80: لا ينطبق | J80: 26161.827 | K80: =+K68+1 -> 2014
A81: الناتج المحلي الإجمالي بالأسعار الجارية | B81: Gross Domestic Product at Current Prices | C81: M1 | D81: Million JD | E81: مليون دينار | F81: Not Applicable | G81: لا ينطبق | H81: =+'Source Table'!$B$13 -> Gov. Final Consumption Expenditures | I81: =+'Source Table'!$D$13 -> الإنفاق الاستهلاكي النهائي الحكومي | J81: 4766.9572 | K81: =+K69+1 -> 2014
A82: الناتج المحلي الإجمالي بالأسعار الجارية | B82: Gross Domestic Product at Current Prices | C82: M1 | D82: Million JD | E82: مليون دينار | F82: Not Applicable | G82: لا ينطبق | H82: =+'Source Table'!$B$14 -> Private Final Consumption Expenditures | I82: =+'Source Table'!$D$14 -> الإنفاق الاستهلاكي النهائي الخاص | J82: 21358.739 | K82: =+K70+1 -> 2014
A83: الناتج المحلي الإجمالي بالأسعار الجارية | B83: Gross Domestic Product at Current Prices | C83: M1 | D83: Million JD | E83: مليون دينار | F83: Not Applicable | G83: لا ينطبق | H83: =+'Source Table'!$B$15 -> Fixed Capital Formation | I83: =+'Source Table'!$D$15 -> التكوين الرأسمالي الثابت | J83: 936.15527 | K83: =+K71+1 -> 2014
A84: الناتج المحلي الإجمالي بالأسعار الجارية | B84: Gross Domestic Product at Current Prices | C84: M1 | D84: Million JD | E84: مليون دينار | F84: Not Applicable | G84: لا ينطبق | H84: =+'Source Table'!$B$16 -> Changes in Stocks | I84: =+'Source Table'!$D$16 -> التغير في المخزون | J84: 5815.9755 | K84: =+K72+1 -> 2014
A85: الناتج المحلي الإجمالي بالأسعار الجارية | B85: Gross Domestic Product at Current Prices | C85: M1 | D85: Million JD | E85: مليون دينار | F85: Not Applicable | G85: لا ينطبق | H85: =+'Source Table'!$B$17 -> Exports of Goods and Services | I85: =+'Source Table'!$D$17 -> صادرات السلع والخدمات | J85: 11023 | K85: =+K73+1 -> 2014
A86: الناتج المحلي الإجمالي بالأسعار الجارية | B86: Gross Domestic Product at Current Prices | C86: M1 | D86: Million JD | E86: مليون دينار | F86: Not Applicable | G86: لا ينطبق | H86: =+'Source Table'!$B$18 -> Less: Imports of Goods and Services | I86: =+'Source Table'!$D$18 -> ناقص: واردات السلع والخدمات | J86: 17739 | K86: =+K74+1 -> 2014
A87: الناتج المحلي الإجمالي بالأسعار الجارية | B87: Gross Domestic Product at Current Prices | C87: M1 | D87: Million JD | E87: مليون دينار | F87: Not Applicable | G87: لا ينطبق | H87: =+'Source Table'!$B$19 -> Gross Domestic Product at Market Prices Expenditure Approach | I87: =+'Source Table'!$D$19 -> الناتج المحلي الاجمالي بأسعار السوق طريقة الإنفاق | J87: 26161.827 | K87: =+K75+1 -> 2014
A88: الناتج المحلي الإجمالي بالأسعار الجارية | B88: Gross Domestic Product at Current Prices | C88: M1 | D88: Million JD | E88: مليون دينار | F88: =+'Source Table'!$B$8 -> Compensation of Employees | G88: =+'Source Table'!$D$8 -> تعويضات العاملين | H88: Not Applicable | I88: لا ينطبق | J88: 10345.023 | K88: =+K76+1 -> 2015
A89: الناتج المحلي الإجمالي بالأسعار الجارية | B89: Gross Domestic Product at Current Prices | C89: M1 | D89: Million JD | E89: مليون دينار | F89: =+'Source Table'!$B$9 -> Operating Surplus | G89: =+'Source Table'!$D$9 -> اجمالي فائض التشغيل والدخل المختلط | H89: Not Applicable | I89: لا ينطبق | J89: 13204.134 | K89: =+K77+1 -> 2015
A90: الناتج المحلي الإجمالي بالأسعار الجارية | B90: Gross Domestic Product at Current Prices | C90: M1 | D90: Million JD | E90: مليون دينار | F90: =+'Source Table'!$B$10 -> Taxes on Production and Products | G90: =+'Source Table'!$D$10 -> الضرائب على الإنتاج والمنتجات | H90: Not Applicable | I90: لا ينطبق | J90: 4042.6258 | K90: =+K78+1 -> 2015
A91: الناتج المحلي الإجمالي بالأسعار الجارية | B91: Gross Domestic Product at Current Prices | C91: M1 | D91: Million JD | E91: مليون دينار | F91: =+'Source Table'!$B$11 -> Less: Subsidies | G91: =+'Source Table'!$D$11 -> ناقص : الإعانات | H91: Not Applicable | I91: لا ينطبق | J91: 195 | K91: =+K79+1 -> 2015
A92: الناتج المحلي الإجمالي بالأسعار الجارية | B92: Gross Domestic Product at Current Prices | C92: M1 | D92: Million JD | E92: مليون دينار | F92: =+'Source Table'!$B$12 -> Gross Domestic Product at Market prices Income Approach | G92: =+'Source Table'!$D$12 -> الناتج المحلي الإجمالي باسعار السوق طريقة الدخل | H92: Not Applicable | I92: لا ينطبق | J92: 27396.783 | K92: =+K80+1 -> 2015
A93: الناتج المحلي الإجمالي بالأسعار الجارية | B93: Gross Domestic Product at Current Prices | C93: M1 | D93: Million JD | E93: مليون دينار | F93: Not Applicable | G93: لا ينطبق | H93: =+'Source Table'!$B$13 -> Gov. Final Consumption Expenditures | I93: =+'Source Table'!$D$13 -> الإنفاق الاستهلاكي النهائي الحكومي | J93: 4882.9772 | K93: =+K81+1 -> 2015
A94: الناتج المحلي الإجمالي بالأسعار الجارية | B94: Gross Domestic Product at Current Prices | C94: M1 | D94: Million JD | E94: مليون دينار | F94: Not Applicable | G94: لا ينطبق | H94: =+'Source Table'!$B$14 -> Private Final Consumption Expenditures | I94: =+'Source Table'!$D$14 -> الإنفاق الاستهلاكي النهائي الخاص | J94: 21810.878 | K94: =+K82+1 -> 2015
A95: الناتج المحلي الإجمالي بالأسعار الجارية | B95: Gross Domestic Product at Current Prices | C95: M1 | D95: Million JD | E95: مليون دينار | F95: Not Applicable | G95: لا ينطبق | H95: =+'Source Table'!$B$15 -> Fixed Capital Formation | I95: =+'Source Table'!$D$15 -> التكوين الرأسمالي الثابت | J95: 822.87621 | K95: =+K83+1 -> 2015
A96: الناتج المحلي الإجمالي بالأسعار الجارية | B96: Gross Domestic Product at Current Prices | C96: M1 | D96: Million JD | E96: مليون دينار | F96: Not Applicable | G96: لا ينطبق | H96: =+'Source Table'!$B$16 -> Changes in Stocks | I96: =+'Source Table'!$D$16 -> التغير في المخزون | J96: 5981.0518 | K96: =+K84+1 -> 2015
A97: الناتج المحلي الإجمالي بالأسعار الجارية | B97: Gross Domestic Product at Current Prices | C97: M1 | D97: Million JD | E97: مليون دينار | F97: Not Applicable | G97: لا ينطبق | H97: =+'Source Table'!$B$17 -> Exports of Goods and Services | I97: =+'Source Table'!$D$17 -> صادرات السلع والخدمات | J97: 10012 | K97: =+K85+1 -> 2015
A98: الناتج المحلي الإجمالي بالأسعار الجارية | B98: Gross Domestic Product at Current Prices | C98: M1 | D98: Million JD | E98: مليون دينار | F98: Not Applicable | G98: لا ينطبق | H98: =+'Source Table'!$B$18 -> Less: Imports of Goods and Services | I98: =+'Source Table'!$D$18 -> ناقص: واردات السلع والخدمات | J98: 16113 | K98: =+K86+1 -> 2015
A99: الناتج المحلي الإجمالي بالأسعار الجارية | B99: Gross Domestic Product at Current Prices | C99: M1 | D99: Million JD | E99: مليون دينار | F99: Not Applicable | G99: لا ينطبق | H99: =+'Source Table'!$B$19 -> Gross Domestic Product at Market Prices Expenditure Approach | I99: =+'Source Table'!$D$19 -> الناتج المحلي الاجمالي بأسعار السوق طريقة الإنفاق | J99: 27396.783 | K99: =+K87+1 -> 2015
A100: الناتج المحلي الإجمالي بالأسعار الجارية | B100: Gross Domestic Product at Current Prices | C100: M1 | D100: Million JD | E100: مليون دينار | F100: =+'Source Table'!$B$8 -> Compensation of Employees | G100: =+'Source Table'!$D$8 -> تعويضات العاملين | H100: Not Applicable | I100: لا ينطبق | J100: 10855.978 | K100: =+K88+1 -> 2016
...

Sheet Template Data
A1: Date | B1: =DATE(B2,B3,1) -> 44927
A2: Year | B2: 2023
A3: Month | B3: 1
A4: Measure_Name_Ar | B4: Measure_Name_En | C4: Measure_ID | D4: Unit_EN | E4: Unit_AR | F4: CL_INCOME_APPROACH_EN_V1 | G4: CL_INCOME_APPROACH_AR_V1 | H4: CL_EXPENDITURE_EN_V1 | I4: CL_EXPENDITURE_APPROACH_AR_V1 | J4: Obs_Value | K4: Time_Period_Y | L4: Time_Period_M
A5: اسم المؤشر | B5: Measure Name | C5: رمز المؤشر | D5: Unit | E5: الوحدة | F5: INCOME APPROACH | G5: طريقة الدخل | H5: EXPENDITURE APPROACH | I5: طريقة الانفاق | J5: قيمة المؤشر | K5: سنة فترة القياس | L5: شهر فترة القياس

Sheet Help
A2: Step 1: Cover Page | C2: الخطوة 1: Cover Page
A4: Update the template information, to ensure that any meta-information about the template, such as the title, version, and description, is accurate and up-to-date. | C4: قم بتحديث معلومات القالب للتأكد من أن أي معلومات وصفية حول القالب، مثل العنوان والإصدار والوصف، دقيقة ومحدثة.
A6: Step 2: Source Table | C6: الخطوة 2: Source Table
A8: Design your template, ensuring that the time period is mapped correctly to the date information in rows 1-3 of the Template Data Sheet. | C8: قم بتصميم القالب الخاص بك، مع التأكد من أن فترة الوقت مرتبطة بشكل صحيح مع معلومات التاريخ في الصفوف 1-3 في ورقة Template Data.
A10: Step 3: Relational Sheet | C10: الخطوة 3: Relational Sheet
A12: Unpivot the data in the source table into a flat format. Follow these guidelines: | C12: قم بتحويل البيانات في جدول المصدر إلى تنسيق مسطح. اتبع هذه الإرشادات:
A13: 1. Blue Columns: Do not change the names of the blue columns. Update the data as per the current template. | C13: 1. الأعمدة الزرقاء: لا تقم بتغيير أسماء الأعمدة الزرقاء. قم بتحديث البيانات وفقًا للقالب الحالي.
A14: 2. Code Lists: Use the naming convention CL_XXX_EN_V# for code lists, where XXX is the name, and V# is the version, conforming with the definitions in the data dictionary. | C14: 2. قوائم الرموز: استخدم قاعدة التسمية CL_XXX_EN_V# لقوائم الرموز، حيث أن XXX هو الاسم و V# هو الإصدار، وفقًا للتعريفات في قاموس البيانات.
A15: 3. Code List Values: Ensure the code list values match the definitions in the data dictionary. | C15: 3. قيم قائمة الرموز: تأكد من أن قيم قائمة الرموز تتوافق مع التعريفات في قاموس البيانات.
A16: 4. Time_Period_M: Leave empty if the data frequency is yearly. | C16: 4. Time_Period_M: اتركها فارغة إذا كانت دورية البيانات سنوية.
A17: 5. Time_Period_M Format: Use one of these formats: | C17: 5. تنسيق Time_Period_M: استخدم أحد التنسيقات التالية:
A18: Numeric: (1, 2, 3, ..., 12) for months. | C18: رقمي: (1، 2، 3، ...، 12) للأشهر.
... A38: Protect the entire workbook to prevent unauthorized or accidental changes to the structure of the file. | C38: قم بحماية الكتاب بأكمله لمنع التغييرات غير المصرح بها أو غير المقصودة على هيكل الملف.
